peplink_api_client/__init__.py
peplink_api_client/api/__init__.py
peplink_api_client/api/default_api.py
peplink_api_client/api_client.py
peplink_api_client/api_response.py
peplink_api_client/configuration.py
peplink_api_client/exceptions.py
peplink_api_client/models/__init__.py
peplink_api_client/models/band_obj.py
peplink_api_client/models/bw_allowance_monitor_obj.py
peplink_api_client/models/carrier_obj.py
peplink_api_client/models/cell_tower_obj.py
peplink_api_client/models/gobi_obj.py
peplink_api_client/models/meid_obj.py
peplink_api_client/models/modem_obj.py
peplink_api_client/models/monthly_allowance_obj.py
peplink_api_client/models/rat_obj.py
peplink_api_client/models/remote_sim_obj.py
peplink_api_client/models/roaming_obj.py
peplink_api_client/models/signal_obj.py
peplink_api_client/models/sim_group_obj.py
peplink_api_client/models/sim_obj.py
peplink_api_client/models/token_request.py
peplink_api_client/models/token_response.py
peplink_api_client/models/wan_status_response.py
peplink_api_client/models/wan_status_response_response_value.py
peplink_api_client/models/wifi_obj.py
peplink_api_client/py.typed
peplink_api_client/rest.py
peplink_api_client-1.0.2.dist-info/METADATA
peplink_api_client-1.0.2.dist-info/WHEEL
peplink_api_client-1.0.2.dist-info/RECORD
